a13x_depinj/__init__.py
a13x_depinj/config.py
a13x_depinj/errors.py
a13x_depinj/registry.py
a13x_depinj/utils.py
a13x_depinj-0.2.0.dist-info/LICENSE
a13x_depinj-0.2.0.dist-info/METADATA
a13x_depinj-0.2.0.dist-info/WHEEL
a13x_depinj-0.2.0.dist-info/top_level.txt
a13x_depinj-0.2.0.dist-info/RECORD
