Metadata-Version: 2.2
Name: a13x-depinj
Version: 0.2.0
Summary: A lightweight dependency injection framework for Python applications
Author: a13x-h
Author-email: a13x-h <a13x.h.cc@gmail.com>
License: MIT License
Project-URL: Homepage, https://github.com/a13xhv01/a13x-depinj.git
Project-URL: Documentation, https://github.com/a13xhv01/a13x-depinj.git#readme
Project-URL: Repository, https://github.com/a13xhv01/a13x-depinj.git
Project-URL: Bug Tracker, https://github.com/a13xhv01/a13x-depinj.git/issues
Keywords: dependency injection,di,ioc,container
Classifier: Development Status :: 4 - Beta
Classifier: Intended Audience :: Developers
Classifier: License :: OSI Approved :: MIT License
Classifier: Programming Language :: Python :: 3
Classifier: Programming Language :: Python :: 3.8
Classifier: Programming Language :: Python :: 3.9
Classifier: Programming Language :: Python :: 3.10
Classifier: Programming Language :: Python :: 3.11
Classifier: Topic :: Software Development :: Libraries :: Python Modules
Requires-Python: >=3.8
License-File: LICENSE
Requires-Dist: pyyaml>=6.0
Provides-Extra: dev
Requires-Dist: pytest>=8.3.4; extra == "dev"
Requires-Dist: pytest-cov>=6.0.0; extra == "dev"
Requires-Dist: black>=25.1.0; extra == "dev"
Requires-Dist: isort>=6.0.0; extra == "dev"
Requires-Dist: mypy>=1.15.0; extra == "dev"
